thonnycontrib/pybricks/__init__.py
thonny_pybricks-0.1.0.dist-info/LICENSE
thonny_pybricks-0.1.0.dist-info/METADATA
thonny_pybricks-0.1.0.dist-info/WHEEL
thonny_pybricks-0.1.0.dist-info/RECORD
